solidbox/__init__.py
solidbox/uow.py
solidbox-0.1.0.dist-info/WHEEL
solidbox-0.1.0.dist-info/METADATA
solidbox-0.1.0.dist-info/RECORD
