Metadata-Version: 2.3
Name: solidbox
Version: 0.1.0
Summary: Composable building blocks for Python backends
Author: Ali Aliyev
Author-email: Ali Aliyev <ali@aliev.me>
Requires-Python: >=3.10
